uvnote/__init__.py
uvnote/cache.py
uvnote/cli.py
uvnote/executor.py
uvnote/generator.py
uvnote/logging_config.py
uvnote/parser.py
uvnote/rebuild_queue.py
uvnote/server.py
uvnote/templates/base.html.j2
uvnote/templates/boot.js.j2
uvnote/templates/head.html.j2
uvnote/templates/scripts.js.j2
uvnote/templates/styles.css.j2
uvnote-0.3.1.dist-info/METADATA
uvnote-0.3.1.dist-info/WHEEL
uvnote-0.3.1.dist-info/entry_points.txt
uvnote-0.3.1.dist-info/RECORD
