Metadata-Version: 2.4
Name: uvnote
Version: 0.3.1
Summary: Stateless, deterministic notebooks with uv and Markdown
Project-URL: Homepage, https://github.com/drbh/uvnote
Project-URL: Repository, https://github.com/drbh/uvnote
Project-URL: Issues, https://github.com/drbh/uvnote/issues
Author: drbh
License: MIT
Keywords: markdown,notebook,python,reproducible,uv
Classifier: Development Status :: 3 - Alpha
Classifier: Intended Audience :: Developers
Classifier: License :: OSI Approved :: MIT License
Classifier: Programming Language :: Python :: 3
Classifier: Programming Language :: Python :: 3.10
Classifier: Programming Language :: Python :: 3.11
Classifier: Programming Language :: Python :: 3.12
Classifier: Topic :: Software Development :: Documentation
Classifier: Topic :: Text Processing :: Markup :: Markdown
Requires-Python: >=3.10
Requires-Dist: click>=8.1.0
Requires-Dist: flask>=3.0.0
Requires-Dist: jinja2>=3.1.0
Requires-Dist: markdown>=3.5.0
Requires-Dist: pygments>=2.16.0
Requires-Dist: pyyaml>=6.0.0
Requires-Dist: watchdog>=3.0.0
Provides-Extra: dev
Requires-Dist: ruff>=0.1.0; extra == 'dev'
